MANIFEST.in
README.md
pyproject.toml
requirements.txt
setup.cfg
setup.py
t_utils/__init__.py
t_utils/const_utils.py
t_utils/datetime_utils.py
t_utils/dict_utils.py
t_utils/excel_utils.py
t_utils/exception_utils.py
t_utils/file_utils.py
t_utils/logger_utils.py
t_utils/num_utils.py
t_utils/robocloud_utils.py
t_utils/thoughthub_utils.py
t_utils/lib_utils/__init__.py
t_utils/lib_utils/logger.py
t_utils_kit.egg-info/PKG-INFO
t_utils_kit.egg-info/SOURCES.txt
t_utils_kit.egg-info/dependency_links.txt
t_utils_kit.egg-info/not-zip-safe
t_utils_kit.egg-info/requires.txt
t_utils_kit.egg-info/top_level.txt
tests/test_t_utils.py