Metadata-Version: 2.4
Name: t_utils_kit
Version: 0.1.15
Summary: t_utils
Home-page: https://www.thoughtful.ai/
Author: Thoughtful
Author-email: support@thoughtful.ai
Keywords: t_utils
Classifier: Intended Audience :: Developers
Classifier: Natural Language :: English
Classifier: Programming Language :: Python :: 3
Classifier: Programming Language :: Python :: 3.9
Requires-Python: >=3.9
Requires-Dist: pandas<3.0.0,>=2.2.3
Requires-Dist: openpyxl<4.0.0,>=3.1.5
Requires-Dist: psutil<=6.1.1,>=5.9.8
Dynamic: author
Dynamic: author-email
Dynamic: classifier
Dynamic: description
Dynamic: description-content-type
Dynamic: home-page
Dynamic: keywords
Dynamic: requires-dist
Dynamic: requires-python
Dynamic: summary
